{
  "schema_version": "1.0",
  "ticket_id": "STUDIO-01",
  "agent": "Test Breaker Agent",
  "captured_at": "2026-05-23T14:30:00Z",
  "todos": [
    {
      "id": "tb-1",
      "content": "Extend StudioLayout.test.tsx — §11 invalid flags, hydration on interaction",
      "status": "completed",
      "agent": "Test Breaker Agent"
    },
    {
      "id": "tb-2",
      "content": "Checkpoint 2026-05-23T-test-break-run.md with verbatim RED npm output",
      "status": "completed",
      "agent": "Test Breaker Agent"
    },
    {
      "id": "tb-3",
      "content": "Update ticket to IMPLEMENTATION_FRONTEND; handoff test_break_to_implementation",
      "status": "completed",
      "agent": "Test Breaker Agent"
    }
  ]
}
